<?xml version="1.0" encoding="UTF-8"?>
<!DOCTYPE mapper PUBLIC "-//mybatis.org//DTD Mapper 3.0//EN" "http://mybatis.org/dtd/mybatis-3-mapper.dtd">
<mapper namespace="cherry.sqlapp.db.gen.mapper.SqltoolMetadataMapper">
  <resultMap id="BaseResultMap" type="cherry.sqlapp.db.gen.dto.SqltoolMetadata">
    <!--
      WARNING - @mbggenerated
      This element is automatically generated by MyBatis Generator, do not modify.
    -->
    <id column="ID" jdbcType="INTEGER" property="id" />
    <result column="SQL_TYPE" jdbcType="VARCHAR" property="sqlType" />
    <result column="NAME" jdbcType="VARCHAR" property="name" />
    <result column="DESCRIPTION" jdbcType="VARCHAR" property="description" />
    <result column="OWNED_BY" jdbcType="VARCHAR" property="ownedBy" />
    <result column="PUBLISHED_FLG" jdbcType="INTEGER" property="publishedFlg" />
    <result column="REGISTERED_AT" jdbcType="TIMESTAMP" property="registeredAt" />
    <result column="UPDATED_AT" jdbcType="TIMESTAMP" property="updatedAt" />
    <result column="CREATED_AT" jdbcType="TIMESTAMP" property="createdAt" />
    <result column="LOCK_VERSION" jdbcType="INTEGER" property="lockVersion" />
    <result column="DELETED_FLG" jdbcType="INTEGER" property="deletedFlg" />
  </resultMap>
  <delete id="deleteByPrimaryKey" parameterType="java.lang.Integer">
    <!--
      WARNING - @mbggenerated
      This element is automatically generated by MyBatis Generator, do not modify.
    -->
    delete from SQLTOOL_METADATA
    where ID = #{id,jdbcType=INTEGER}
  </delete>
  <insert id="insert" parameterType="cherry.sqlapp.db.gen.dto.SqltoolMetadata">
    <!--
      WARNING - @mbggenerated
      This element is automatically generated by MyBatis Generator, do not modify.
    -->
    insert into SQLTOOL_METADATA (ID, SQL_TYPE, NAME, 
      DESCRIPTION, OWNED_BY, PUBLISHED_FLG, 
      REGISTERED_AT, UPDATED_AT, CREATED_AT, 
      LOCK_VERSION, DELETED_FLG)
    values (#{id,jdbcType=INTEGER}, #{sqlType,jdbcType=VARCHAR}, #{name,jdbcType=VARCHAR}, 
      #{description,jdbcType=VARCHAR}, #{ownedBy,jdbcType=VARCHAR}, #{publishedFlg,jdbcType=INTEGER}, 
      #{registeredAt,jdbcType=TIMESTAMP}, #{updatedAt,jdbcType=TIMESTAMP}, #{createdAt,jdbcType=TIMESTAMP}, 
      #{lockVersion,jdbcType=INTEGER}, #{deletedFlg,jdbcType=INTEGER})
  </insert>
  <update id="updateByPrimaryKey" parameterType="cherry.sqlapp.db.gen.dto.SqltoolMetadata">
    <!--
      WARNING - @mbggenerated
      This element is automatically generated by MyBatis Generator, do not modify.
    -->
    update SQLTOOL_METADATA
    set SQL_TYPE = #{sqlType,jdbcType=VARCHAR},
      NAME = #{name,jdbcType=VARCHAR},
      DESCRIPTION = #{description,jdbcType=VARCHAR},
      OWNED_BY = #{ownedBy,jdbcType=VARCHAR},
      PUBLISHED_FLG = #{publishedFlg,jdbcType=INTEGER},
      REGISTERED_AT = #{registeredAt,jdbcType=TIMESTAMP},
      UPDATED_AT = #{updatedAt,jdbcType=TIMESTAMP},
      CREATED_AT = #{createdAt,jdbcType=TIMESTAMP},
      LOCK_VERSION = #{lockVersion,jdbcType=INTEGER},
      DELETED_FLG = #{deletedFlg,jdbcType=INTEGER}
    where ID = #{id,jdbcType=INTEGER}
  </update>
  <select id="selectByPrimaryKey" parameterType="java.lang.Integer" resultMap="BaseResultMap">
    <!--
      WARNING - @mbggenerated
      This element is automatically generated by MyBatis Generator, do not modify.
    -->
    select ID, SQL_TYPE, NAME, DESCRIPTION, OWNED_BY, PUBLISHED_FLG, REGISTERED_AT, UPDATED_AT, 
    CREATED_AT, LOCK_VERSION, DELETED_FLG
    from SQLTOOL_METADATA
    where ID = #{id,jdbcType=INTEGER}
  </select>
  <select id="selectAll" resultMap="BaseResultMap">
    <!--
      WARNING - @mbggenerated
      This element is automatically generated by MyBatis Generator, do not modify.
    -->
    select ID, SQL_TYPE, NAME, DESCRIPTION, OWNED_BY, PUBLISHED_FLG, REGISTERED_AT, UPDATED_AT, 
    CREATED_AT, LOCK_VERSION, DELETED_FLG
    from SQLTOOL_METADATA
  </select>
</mapper>